deepKernel/__init__.py
deepKernel/base.py
deepKernel/configuration.py
deepKernel/deepline.py
deepKernel/edition.py
deepKernel/information.py
deepKernel/input.py
deepKernel/output.py
deepkernel-0.0.22.dist-info/licenses/LICENSE
deepkernel-0.0.22.dist-info/METADATA
deepkernel-0.0.22.dist-info/WHEEL
deepkernel-0.0.22.dist-info/top_level.txt
deepkernel-0.0.22.dist-info/RECORD
