Metadata-Version: 2.4
Name: deepKernel
Version: 0.0.22
Summary: A simple example package
Home-page: https://www.pzeda.com/CN
Author: pz
Author-email: meichiyuan@pzeda.com
Classifier: Programming Language :: Python :: 3
Classifier: License :: OSI Approved :: GNU General Public License v3 (GPLv3)
Classifier: Operating System :: OS Independent
Requires-Python: >=3.6
License-File: LICENSE
Requires-Dist: pillow>=11.2.1
Requires-Dist: numpy>=2.2.6
Dynamic: author
Dynamic: author-email
Dynamic: classifier
Dynamic: description
Dynamic: description-content-type
Dynamic: home-page
Dynamic: license-file
Dynamic: requires-dist
Dynamic: requires-python
Dynamic: summary
